odoorpc/__init__.py
odoorpc/db.py
odoorpc/env.py
odoorpc/error.py
odoorpc/fields.py
odoorpc/models.py
odoorpc/odoo.py
odoorpc/report.py
odoorpc/session.py
odoorpc/tools.py
odoorpc/rpc/__init__.py
odoorpc/rpc/error.py
odoorpc/rpc/jsonrpclib.py
OdooRPC-0.7.0.dist-info/AUTHORS
OdooRPC-0.7.0.dist-info/LICENSE
OdooRPC-0.7.0.dist-info/METADATA
OdooRPC-0.7.0.dist-info/WHEEL
OdooRPC-0.7.0.dist-info/top_level.txt
OdooRPC-0.7.0.dist-info/RECORD
