Metadata-Version: 2.1
Name: OdooRPC
Version: 0.7.0
Summary: OdooRPC is a Python package providing an easy way to pilot your Odoo servers through RPC.
Home-page: https://github.com/OCA/odoorpc
Author: Sebastien Alix
Author-email: seb@usr-src.org
License: LGPL v3
Keywords: openerp odoo server rpc client xml-rpc xmlrpc jsonrpc json-rpc odoorpc oerplib communication lib library python service web webservice
Platform: UNKNOWN
Classifier: Intended Audience :: Developers
Classifier: Programming Language :: Python
Classifier: Programming Language :: Python :: 2
Classifier: Programming Language :: Python :: 2.7
Classifier: Programming Language :: Python :: 3
Classifier: Programming Language :: Python :: 3.4
Classifier: Programming Language :: Python :: 3.5
Classifier: Programming Language :: Python :: 3.6
Classifier: Programming Language :: Python :: Implementation :: CPython
Classifier: Programming Language :: Python :: Implementation :: PyPy
Classifier: License :: OSI Approved :: GNU Library or Lesser General Public License (LGPL)
Classifier: Topic :: Software Development :: Libraries :: Python Modules
Classifier: Framework :: Odoo
